{"topic_56": {"num_tags": 21, "name": "topic_56", "full_name": "topic_56", "num_included_tokens": 21}, "topic_55": {"num_tags": 17, "name": "topic_55", "full_name": "topic_55", "num_included_tokens": 17}, "topic_18": {"num_tags": 6, "name": "topic_18", "full_name": "topic_18", "num_included_tokens": 6}, "topic_28": {"num_tags": 7, "name": "topic_28", "full_name": "topic_28", "num_included_tokens": 7}, "topic_79": {"num_tags": 6, "name": "topic_79", "full_name": "topic_79", "num_included_tokens": 6}, "topic_26": {"num_tags": 5, "name": "topic_26", "full_name": "topic_26", "num_included_tokens": 5}, "topic_38": {"num_tags": 24, "name": "topic_38", "full_name": "topic_38", "num_included_tokens": 24}, "topic_87": {"num_tags": 4, "name": "topic_87", "full_name": "topic_87", "num_included_tokens": 4}, "topic_49": {"num_tags": 17, "name": "topic_49", "full_name": "topic_49", "num_included_tokens": 17}, "topic_80": {"num_tags": 3, "name": "topic_80", "full_name": "topic_80", "num_included_tokens": 3}, "topic_92": {"num_tags": 24, "name": "topic_92", "full_name": "topic_92", "num_included_tokens": 24}, "topic_83": {"num_tags": 11, "name": "topic_83", "full_name": "topic_83", "num_included_tokens": 11}, "topic_93": {"num_tags": 4, "name": "topic_93", "full_name": "topic_93", "num_included_tokens": 4}, "topic_64": {"num_tags": 3, "name": "topic_64", "full_name": "topic_64", "num_included_tokens": 3}, "topic_94": {"num_tags": 5, "name": "topic_94", "full_name": "topic_94", "num_included_tokens": 5}, "topic_75": {"num_tags": 8, "name": "topic_75", "full_name": "topic_75", "num_included_tokens": 8}, "topic_97": {"num_tags": 5, "name": "topic_97", "full_name": "topic_97", "num_included_tokens": 5}, "topic_27": {"num_tags": 1, "name": "topic_27", "full_name": "topic_27", "num_included_tokens": 1}, "topic_76": {"num_tags": 3, "name": "topic_76", "full_name": "topic_76", "num_included_tokens": 3}, "topic_9": {"num_tags": 23, "name": "topic_9", "full_name": "topic_9", "num_included_tokens": 23}}