{"topic_30": {"num_tags": 15, "name": "topic_30", "full_name": "topic_30", "num_included_tokens": 15}, "topic_42": {"num_tags": 46, "name": "topic_42", "full_name": "topic_42", "num_included_tokens": 46}, "topic_43": {"num_tags": 6, "name": "topic_43", "full_name": "topic_43", "num_included_tokens": 6}, "topic_24": {"num_tags": 30, "name": "topic_24", "full_name": "topic_24", "num_included_tokens": 30}, "topic_10": {"num_tags": 11, "name": "topic_10", "full_name": "topic_10", "num_included_tokens": 11}, "topic_22": {"num_tags": 14, "name": "topic_22", "full_name": "topic_22", "num_included_tokens": 14}, "topic_11": {"num_tags": 1, "name": "topic_11", "full_name": "topic_11", "num_included_tokens": 1}}